zipeggs.py
zipeggs-1.0.1.dist-info/DESCRIPTION.rst
zipeggs-1.0.1.dist-info/METADATA
zipeggs-1.0.1.dist-info/RECORD
zipeggs-1.0.1.dist-info/WHEEL
zipeggs-1.0.1.dist-info/entry_points.txt
zipeggs-1.0.1.dist-info/metadata.json
zipeggs-1.0.1.dist-info/top_level.txt
