Metadata-Version: 2.0
Name: zipeggs
Version: 1.0.1
Summary: Zip flattened out eggs back again
Home-page: https://github.com/tamizhgeek/zipeggs
Author: Azhagu Selvan
Author-email: UNKNOWN
License: Apache 2.0
Platform: UNKNOWN
